cis_checks_2023_u1/__init__.py
cis_checks_2023_u1/_security_control_5.py
cis_checks_2023_u1/iam_control_1.py
cis_checks_2023_u1/logging_control_3.py
cis_checks_2023_u1/monitoring_control_4.py
cis_checks_2023_u1/networking_control_5.py
cis_checks_2023_u1/storage_control_2.py
cis_checks_2023_u1/utils.py
cis_checks_2023_u1-2.1.1.dist-info/METADATA
cis_checks_2023_u1-2.1.1.dist-info/WHEEL
cis_checks_2023_u1-2.1.1.dist-info/top_level.txt
cis_checks_2023_u1-2.1.1.dist-info/RECORD
